{
  "retailer": "1stDibs",
  "product_id": "f_44096252",
  "name": "Ico Parisi, rare set of 6 walnut chairs with butterfly backrest",
  "slug": "f_44096252",
  "price": "CA$22,402.39",
  "description": "",
  "image_url": "https://a.1stdibscdn.com/ico-parisi-rare-set-of-6-walnut-chairs-with-butterfly-backrest-for-sale/f_82582/f_440962521742295434848/f_44096252_1742295435055_bg_processed.jpg",
  "url": "https://www.1stdibs.com/furniture/seating/chairs/ico-parisi-rare-set-of-6-walnut-chairs-butterfly-backrest/id-f_44096252/",
  "specifications": {
    "dimensions": {
      "height": "Height: 31.5 in (80 cm)",
      "width": "Width: 19.69 in (50 cm)",
      "depth": "Depth: 19.69 in (50 cm)",
      "seatHeight": "Seat Height: 16.54 in (42 cm)"
    },
    "style": "Mid-Century Modern (Of the Period)",
    "materials": [
      "Walnut",
      "Walnut"
    ],
    "origin": "Italy",
    "period": "Mid-20th Century",
    "dateOfManufacture": "1952",
    "condition": {
      "rating": "Excellent",
      "details": "Refinished. The price include the reupholstery with plane color in cotton or velvet."
    },
    "sellerLocation": "Milano, IT",
    "referenceNumber": "1stDibs: LU8258244096252",
    "rawSpecificationsHTML": "<div id=\":Ropiha:\" data-tn=\"expanding-area\" data-state=\"collapsed\" class=\"_85f5162c _473e3111\" style=\"height: auto;\"><div data-tn=\"expanding-area-children-wrapper\" class=\"_98acf5a0\"><span class=\"_dda3618c\" data-tn=\"pdp-item-description-content\">Ico Parisi (1916-1996)\n\nRare set of 6 walnut chairs with butterfly backrest.\n\nManufactured by F.lli Colombo, Como, 1952.</span></div></div>",
    "rawSpecificationsText": "Ico Parisi (1916-1996)\n\nRare set of 6 walnut chairs with butterfly backrest.\n\nManufactured by F.lli Colombo, Como, 1952."
  },
  "raw_data": {
    "productId": "f_44096252",
    "slug": "f_44096252",
    "url": "https://www.1stdibs.com/furniture/seating/chairs/ico-parisi-rare-set-of-6-walnut-chairs-butterfly-backrest/id-f_44096252/",
    "name": "Ico Parisi, rare set of 6 walnut chairs with butterfly backrest",
    "price": "CA$22,402.39",
    "imageUrl": "https://a.1stdibscdn.com/ico-parisi-rare-set-of-6-walnut-chairs-with-butterfly-backrest-for-sale/f_82582/f_440962521742295434848/f_44096252_1742295435055_bg_processed.jpg",
    "description": "",
    "specifications": {
      "dimensions": {
        "height": "Height: 31.5 in (80 cm)",
        "width": "Width: 19.69 in (50 cm)",
        "depth": "Depth: 19.69 in (50 cm)",
        "seatHeight": "Seat Height: 16.54 in (42 cm)"
      },
      "style": "Mid-Century Modern (Of the Period)",
      "materials": [
        "Walnut",
        "Walnut"
      ],
      "origin": "Italy",
      "period": "Mid-20th Century",
      "dateOfManufacture": "1952",
      "condition": {
        "rating": "Excellent",
        "details": "Refinished. The price include the reupholstery with plane color in cotton or velvet."
      },
      "sellerLocation": "Milano, IT",
      "referenceNumber": "1stDibs: LU8258244096252",
      "rawSpecificationsHTML": "<div id=\":Ropiha:\" data-tn=\"expanding-area\" data-state=\"collapsed\" class=\"_85f5162c _473e3111\" style=\"height: auto;\"><div data-tn=\"expanding-area-children-wrapper\" class=\"_98acf5a0\"><span class=\"_dda3618c\" data-tn=\"pdp-item-description-content\">Ico Parisi (1916-1996)\n\nRare set of 6 walnut chairs with butterfly backrest.\n\nManufactured by F.lli Colombo, Como, 1952.</span></div></div>",
      "rawSpecificationsText": "Ico Parisi (1916-1996)\n\nRare set of 6 walnut chairs with butterfly backrest.\n\nManufactured by F.lli Colombo, Como, 1952."
    },
    "jsonLd": null,
    "extractionMethod": "manual"
  }
}